mflux_fasthtml/__about__.py
mflux_fasthtml/__init__.py
mflux_fasthtml/__main__.py
mflux_fasthtml/cli/__init__.py
mflux_fasthtml-0.0.1.dist-info/METADATA
mflux_fasthtml-0.0.1.dist-info/WHEEL
mflux_fasthtml-0.0.1.dist-info/entry_points.txt
mflux_fasthtml-0.0.1.dist-info/licenses/LICENSE.txt
mflux_fasthtml-0.0.1.dist-info/RECORD
